qas/__init__.py
qas/basic_details.py
qas/company_name.py
qas/constants.py
qas/designation.py
qas/education.py
qas/get_context.py
qas/llm.py
qas/nlp.py
qas/skills.py
qas/test.py
qasi-0.1.5.dist-info/licenses/LICENSE
qasi-0.1.5.dist-info/METADATA
qasi-0.1.5.dist-info/WHEEL
qasi-0.1.5.dist-info/top_level.txt
qasi-0.1.5.dist-info/RECORD
