Metadata-Version: 2.4
Name: qasi
Version: 0.1.5
Summary: AI assistant for answering job application questions
Home-page: https://github.com/Job-automation/qas.git
Author: Prasanna Gramopadhye
Author-email: gramopadhye37@gmail.com
Classifier: Programming Language :: Python :: 3
Classifier: Operating System :: OS Independent
Requires-Python: >=3.7
License-File: LICENSE
Requires-Dist: requests==2.32.3
Requires-Dist: transformers==4.51.3
Requires-Dist: spacy==3.8.5
Requires-Dist: pdfminer.six==20250327
Requires-Dist: tf_keras==2.19.0
Requires-Dist: tensorflow==2.19.0
Requires-Dist: torch==2.6.0
Dynamic: author
Dynamic: author-email
Dynamic: classifier
Dynamic: description
Dynamic: description-content-type
Dynamic: home-page
Dynamic: license-file
Dynamic: requires-dist
Dynamic: requires-python
Dynamic: summary
